sizeroyale/__init__.py
sizeroyale/__main__.py
sizeroyale/main.py
sizeroyale/cogs/__init__.py
sizeroyale/cogs/royale.py
sizeroyale/lib/__init__.py
sizeroyale/lib/embedtemplate.py
sizeroyale/lib/errors.py
sizeroyale/lib/img_utils.py
sizeroyale/lib/listdict.py
sizeroyale/lib/runnableevent.py
sizeroyale/lib/classes/__init__.py
sizeroyale/lib/classes/arena.py
sizeroyale/lib/classes/dummyplayer.py
sizeroyale/lib/classes/event.py
sizeroyale/lib/classes/game.py
sizeroyale/lib/classes/metaparser.py
sizeroyale/lib/classes/parser.py
sizeroyale/lib/classes/player.py
sizeroyale/lib/classes/royale.py
sizeroyale/lib/classes/setup.py
sizeroyale-1.0.5.dist-info/LICENSE
sizeroyale-1.0.5.dist-info/METADATA
sizeroyale-1.0.5.dist-info/WHEEL
sizeroyale-1.0.5.dist-info/top_level.txt
sizeroyale-1.0.5.dist-info/zip-safe
sizeroyale-1.0.5.dist-info/RECORD
