Metadata-Version: 2.1
Name: sizeroyale
Version: 1.0.5
Summary: sizeroyale
Home-page: UNKNOWN
Author: DigiDuncan
Author-email: digiduncan@gmail.com
License: GPLv3
Project-URL: Source, https://github.com/sizedev/sizeroyale
Project-URL: Tracker, https://github.com/sizedev/sizeroyale/issues
Keywords: sizebot,sizeroyale
Platform: any
Classifier: Programming Language :: Python :: 3.8
Classifier: Operating System :: OS Independent
Classifier: License :: OSI Approved :: GNU General Public License v3 (GPLv3)
Requires-Python: >=3.8
License-File: LICENSE
Provides-Extra: dev
Requires-Dist: autopep8 (==1.5.5) ; extra == 'dev'
Requires-Dist: flake8 (==3.8.4) ; extra == 'dev'
